[
	{
		"cmyk": [
			0,
			0,
			0,
			0
		],
		"rgb": [
			255,
			255,
			255
		]
	},
	{
		"cmyk": [
			100,
			24.82677,
			60.67658,
			39.95137
		],
		"rgb": [
			0,
			72,
			96
		]
	},
	{
		"cmyk": [
			68.41488,
			18.32939,
			78.63384,
			29.73665
		],
		"rgb": [
			55,
			139,
			83
		]
	},
	{
		"cmyk": [
			83.37842,
			39.1426,
			74.8813,
			7.551752
		],
		"rgb": [
			9,
			99,
			81
		]
	},
	{
		"cmyk": [
			0,
			24.02507,
			49.14707,
			100
		],
		"rgb": [
			30,
			2,
			0
		]
	},
	{
		"cmyk": [
			28.57143,
			0,
			0,
			0
		],
		"rgb": [
			180,
			229,
			251
		]
	},
	{
		"cmyk": [
			42.85714,
			0,
			0,
			0
		],
		"rgb": [
			140,
			211,
			248
		]
	},
	{
		"cmyk": [
			57.14286,
			0,
			0,
			0
		],
		"rgb": [
			94,
			187,
			240
		]
	},
	{
		"cmyk": [
			71.42857,
			0,
			0,
			0
		],
		"rgb": [
			22,
			158,
			227
		]
	},
	{
		"cmyk": [
			85.71429,
			0,
			0,
			0
		],
		"rgb": [
			0,
			120,
			206
		]
	},
	{
		"cmyk": [
			100,
			0,
			0,
			0
		],
		"rgb": [
			0,
			79,
			178
		]
	},
	{
		"cmyk": [
			0,
			14.28571,
			0,
			0
		],
		"rgb": [
			255,
			225,
			241
		]
	},
	{
		"cmyk": [
			0,
			28.57143,
			0,
			0
		],
		"rgb": [
			255,
			195,
			225
		]
	},
	{
		"cmyk": [
			0,
			42.85714,
			0,
			0
		],
		"rgb": [
			255,
			165,
			208
		]
	},
	{
		"cmyk": [
			0,
			57.14286,
			0,
			0
		],
		"rgb": [
			255,
			130,
			183
		]
	},
	{
		"cmyk": [
			0,
			71.42857,
			0,
			0
		],
		"rgb": [
			255,
			91,
			152
		]
	},
	{
		"cmyk": [
			0,
			85.71429,
			0,
			0
		],
		"rgb": [
			255,
			35,
			112
		]
	},
	{
		"cmyk": [
			0,
			100,
			0,
			0
		],
		"rgb": [
			233,
			0,
			56
		]
	},
	{
		"cmyk": [
			0,
			0,
			14.28571,
			0
		],
		"rgb": [
			254,
			255,
			227
		]
	},
	{
		"cmyk": [
			0,
			0,
			28.57143,
			0
		],
		"rgb": [
			251,
			255,
			199
		]
	},
	{
		"cmyk": [
			0,
			0,
			42.85714,
			0
		],
		"rgb": [
			251,
			255,
			171
		]
	},
	{
		"cmyk": [
			0,
			0,
			57.14286,
			0
		],
		"rgb": [
			251,
			255,
			139
		]
	},
	{
		"cmyk": [
			0,
			0,
			71.42857,
			0
		],
		"rgb": [
			253,
			255,
			98
		]
	},
	{
		"cmyk": [
			0,
			0,
			85.71429,
			0
		],
		"rgb": [
			255,
			251,
			24
		]
	},
	{
		"cmyk": [
			0,
			0,
			100,
			0
		],
		"rgb": [
			255,
			241,
			0
		]
	},
	{
		"cmyk": [
			0,
			0,
			0,
			14.28571
		],
		"rgb": [
			227,
			227,
			227
		]
	},
	{
		"cmyk": [
			0,
			0,
			0,
			28.57143
		],
		"rgb": [
			198,
			195,
			196
		]
	},
	{
		"cmyk": [
			0,
			0,
			0,
			42.85714
		],
		"rgb": [
			169,
			163,
			162
		]
	},
	{
		"cmyk": [
			0,
			0,
			0,
			57.14286
		],
		"rgb": [
			137,
			129,
			129
		]
	},
	{
		"cmyk": [
			0,
			0,
			0,
			71.42857
		],
		"rgb": [
			103,
			91,
			92
		]
	},
	{
		"cmyk": [
			0,
			0,
			0,
			85.71429
		],
		"rgb": [
			66,
			48,
			51
		]
	},
	{
		"cmyk": [
			0,
			0,
			0,
			100
		],
		"rgb": [
			31,
			0,
			0
		]
	},
	{
		"cmyk": [
			14.28571,
			14.28571,
			14.28571,
			0
		],
		"rgb": [
			227,
			221,
			219
		]
	},
	{
		"cmyk": [
			28.57143,
			28.57143,
			28.57143,
			0
		],
		"rgb": [
			198,
			188,
			185
		]
	},
	{
		"cmyk": [
			42.85714,
			42.85714,
			42.85714,
			0
		],
		"rgb": [
			168,
			154,
			150
		]
	},
	{
		"cmyk": [
			57.14286,
			57.14286,
			57.14286,
			0
		],
		"rgb": [
			133,
			118,
			114
		]
	},
	{
		"cmyk": [
			71.42857,
			71.42857,
			71.42857,
			0
		],
		"rgb": [
			98,
			76,
			71
		]
	},
	{
		"cmyk": [
			85.71429,
			85.71429,
			85.71429,
			0
		],
		"rgb": [
			55,
			38,
			30
		]
	},
	{
		"cmyk": [
			100,
			100,
			100,
			0
		],
		"rgb": [
			35,
			11,
			3
		]
	},
	{
		"cmyk": [
			0,
			30.39282,
			19.79549,
			100
		],
		"rgb": [
			30,
			0,
			0
		]
	},
	{
		"cmyk": [
			0,
			0,
			0,
			74.98269
		],
		"rgb": [
			94,
			81,
			82
		]
	},
	{
		"cmyk": [
			0,
			0,
			0,
			61.25011
		],
		"rgb": [
			127,
			119,
			119
		]
	},
	{
		"cmyk": [
			0,
			0,
			0,
			47.37361
		],
		"rgb": [
			158,
			152,
			152
		]
	},
	{
		"cmyk": [
			0,
			0,
			0,
			32.41175
		],
		"rgb": [
			190,
			187,
			187
		]
	},
	{
		"cmyk": [
			0,
			0,
			0,
			16.5915
		],
		"rgb": [
			222,
			222,
			222
		]
	},
	{
		"cmyk": [
			0,
			100,
			100,
			100
		],
		"rgb": [
			57,
			0,
			0
		]
	},
	{
		"cmyk": [
			100,
			0,
			100,
			100
		],
		"rgb": [
			0,
			17,
			0
		]
	},
	{
		"cmyk": [
			100,
			100,
			0,
			100
		],
		"rgb": [
			17,
			0,
			9
		]
	},
	{
		"cmyk": [
			0,
			0,
			100,
			100
		],
		"rgb": [
			33,
			4,
			0
		]
	},
	{
		"cmyk": [
			100,
			0,
			0,
			100
		],
		"rgb": [
			0,
			3,
			5
		]
	},
	{
		"cmyk": [
			0,
			100,
			0,
			100
		],
		"rgb": [
			42,
			0,
			0
		]
	},
	{
		"cmyk": [
			100,
			0,
			100,
			0
		],
		"rgb": [
			0,
			87,
			40
		]
	},
	{
		"cmyk": [
			100,
			100,
			0,
			0
		],
		"rgb": [
			40,
			0,
			68
		]
	},
	{
		"cmyk": [
			0,
			100,
			100,
			0
		],
		"rgb": [
			232,
			0,
			0
		]
	},
	{
		"cmyk": [
			100,
			71.29756,
			100,
			38.70244
		],
		"rgb": [
			0,
			3,
			0
		]
	},
	{
		"cmyk": [
			41.46569,
			68.53431,
			100,
			100
		],
		"rgb": [
			15,
			0,
			0
		]
	},
	{
		"cmyk": [
			68.45866,
			100,
			100,
			41.54134
		],
		"rgb": [
			80,
			0,
			0
		]
	},
	{
		"cmyk": [
			54.65846,
			100,
			55.34154,
			100
		],
		"rgb": [
			34,
			0,
			0
		]
	},
	{
		"cmyk": [
			100,
			100,
			47.30456,
			62.69544
		],
		"rgb": [
			20,
			7,
			29
		]
	},
	{
		"cmyk": [
			100,
			40.62995,
			69.37005,
			100
		],
		"rgb": [
			0,
			6,
			0
		]
	},
	{
		"cmyk": [
			0,
			0,
			100,
			40.04982
		],
		"rgb": [
			180,
			170,
			0
		]
	},
	{
		"cmyk": [
			0,
			100,
			100,
			40.80055
		],
		"rgb": [
			198,
			0,
			0
		]
	},
	{
		"cmyk": [
			0,
			100,
			0,
			60.91181
		],
		"rgb": [
			151,
			0,
			44
		]
	},
	{
		"cmyk": [
			100,
			0,
			0,
			61.07027
		],
		"rgb": [
			0,
			63,
			108
		]
	},
	{
		"cmyk": [
			100,
			0,
			100,
			59.18698
		],
		"rgb": [
			0,
			73,
			29
		]
	},
	{
		"cmyk": [
			0,
			38.13747,
			100,
			0
		],
		"rgb": [
			255,
			178,
			0
		]
	},
	{
		"cmyk": [
			79.29886,
			0,
			100,
			0
		],
		"rgb": [
			0,
			138,
			37
		]
	},
	{
		"cmyk": [
			100,
			0,
			74.17136,
			0
		],
		"rgb": [
			0,
			90,
			96
		]
	},
	{
		"cmyk": [
			59.83376,
			100,
			0,
			0
		],
		"rgb": [
			128,
			0,
			58
		]
	},
	{
		"cmyk": [
			100,
			34.29131,
			0,
			0
		],
		"rgb": [
			0,
			70,
			167
		]
	},
	{
		"cmyk": [
			100,
			100,
			0,
			59.91384
		],
		"rgb": [
			34,
			0,
			51
		]
	},
	{
		"cmyk": [
			0,
			100,
			60.15505,
			0
		],
		"rgb": [
			233,
			0,
			36
		]
	},
	{
		"cmyk": [
			0,
			75.40927,
			100,
			100
		],
		"rgb": [
			39,
			0,
			0
		]
	},
	{
		"cmyk": [
			26.89937,
			0,
			100,
			100
		],
		"rgb": [
			32,
			10,
			0
		]
	},
	{
		"cmyk": [
			59.9983,
			100,
			0,
			100
		],
		"rgb": [
			31,
			0,
			0
		]
	},
	{
		"cmyk": [
			48.98534,
			0,
			0,
			100
		],
		"rgb": [
			23,
			0,
			0
		]
	},
	{
		"cmyk": [
			100,
			49.34352,
			0,
			100
		],
		"rgb": [
			0,
			3,
			5
		]
	},
	{
		"cmyk": [
			100,
			23.56769,
			100,
			0
		],
		"rgb": [
			0,
			80,
			36
		]
	},
	{
		"cmyk": [
			0,
			100,
			59.85614,
			100
		],
		"rgb": [
			52,
			0,
			0
		]
	},
	{
		"cmyk": [
			100,
			0,
			48.55505,
			100
		],
		"rgb": [
			0,
			0,
			0
		]
	},
	{
		"cmyk": [
			100,
			100,
			49.64622,
			0
		],
		"rgb": [
			15,
			0,
			18
		]
	},
	{
		"cmyk": [
			40.07035,
			100,
			100,
			0
		],
		"rgb": [
			163,
			0,
			0
		]
	},
	{
		"cmyk": [
			0,
			0,
			24.71702,
			100
		],
		"rgb": [
			31,
			0,
			0
		]
	},
	{
		"cmyk": [
			35.2316,
			100,
			100,
			74.7684
		],
		"rgb": [
			100,
			0,
			0
		]
	},
	{
		"cmyk": [
			100,
			100,
			76.51508,
			33.48492
		],
		"rgb": [
			0,
			0,
			0
		]
	},
	{
		"cmyk": [
			100,
			55.95063,
			100,
			54.04937
		],
		"rgb": [
			0,
			33,
			0
		]
	},
	{
		"cmyk": [
			0,
			54.77906,
			100,
			50.64467
		],
		"rgb": [
			164,
			104,
			0
		]
	},
	{
		"cmyk": [
			100,
			72.18574,
			37.81426,
			100
		],
		"rgb": [
			0,
			1,
			5
		]
	},
	{
		"cmyk": [
			38.57413,
			0,
			100,
			0
		],
		"rgb": [
			165,
			210,
			0
		]
	},
	{
		"cmyk": [
			0,
			0,
			100,
			78.73088
		],
		"rgb": [
			86,
			74,
			0
		]
	},
	{
		"cmyk": [
			100,
			0,
			49.89628,
			0
		],
		"rgb": [
			0,
			88,
			134
		]
	},
	{
		"cmyk": [
			0,
			0,
			30.21562,
			80.67524
		],
		"rgb": [
			79,
			64,
			61
		]
	},
	{
		"cmyk": [
			72.80413,
			0,
			100,
			75.71806
		],
		"rgb": [
			39,
			73,
			4
		]
	},
	{
		"cmyk": [
			0,
			100,
			100,
			80.74067
		],
		"rgb": [
			108,
			0,
			0
		]
	},
	{
		"cmyk": [
			26.72937,
			0,
			0,
			41.31627
		],
		"rgb": [
			144,
			162,
			166
		]
	},
	{
		"cmyk": [
			0,
			79.75003,
			0,
			100
		],
		"rgb": [
			37,
			0,
			0
		]
	},
	{
		"cmyk": [
			100,
			0,
			35.14798,
			41.49549
		],
		"rgb": [
			0,
			77,
			124
		]
	},
	{
		"cmyk": [
			0,
			54.19287,
			0,
			61.82868
		],
		"rgb": [
			135,
			86,
			106
		]
	},
	{
		"cmyk": [
			100,
			0,
			0,
			41.43753
		],
		"rgb": [
			0,
			74,
			141
		]
	},
	{
		"cmyk": [
			24.82797,
			100,
			85.17203,
			100
		],
		"rgb": [
			44,
			0,
			0
		]
	}
]